pyruicore/__init__.py
pyruicore/data_type/__init__.py
pyruicore/data_type/analysis.py
pyruicore/data_type/basic.py
pyruicore/data_type/const.py
pyruicore/data_type/udf.py
pyruicore/data_type/util.py
pyruicore/field.py
pyruicore/model/__init__.py
pyruicore/model/base.py
pyruicore/model/meta.py
pyruicore-0.1.3.dist-info/LICENSE
pyruicore-0.1.3.dist-info/WHEEL
pyruicore-0.1.3.dist-info/METADATA
pyruicore-0.1.3.dist-info/RECORD
