Metadata-Version: 2.1
Name: pyruicore
Version: 0.1.3
Summary: load python dict data to python class
Home-page: https://github.com/RuiCoreSci/pyruicore
License: MIT
Author: ruicore
Author-email: hrui835@gmail.com
Requires-Python: >=3.8,<4.0
Classifier: License :: OSI Approved :: MIT License
Classifier: Programming Language :: Python :: 3
Classifier: Programming Language :: Python :: 3.8
Classifier: Programming Language :: Python :: 3.9
Requires-Dist: typing (>=3.7.4,<4.0.0)
Project-URL: Repository, https://github.com/RuiCoreSci/pyruicore
